bluexpress/connector.py
bluexpress/handler.py
bluexpress/settings.py
corona_bluexpress_logistica-1.5.16.dist-info/licenses/LICENSE
corona_bluexpress_logistica-1.5.16.dist-info/METADATA
corona_bluexpress_logistica-1.5.16.dist-info/WHEEL
corona_bluexpress_logistica-1.5.16.dist-info/top_level.txt
corona_bluexpress_logistica-1.5.16.dist-info/RECORD
